{
  "country": "France",
  "last_updated": "2026-05-11T23:55:12.310864+00:00",
  "story_count": 93,
  "stories": [
    {
      "title": "France woos Anglophone Africa at a summit in Kenya",
      "source": "France 24",
      "url": "https://www.france24.com/en/france-woos-anglophone-africa-at-a-summit-in-kenya",
      "published_date": "2026-05-11T20:37:07+00:00",
      "category": "Diplomacy"
    },
    {
      "title": "'Macron always been a strong believer in the importance of Africa as a partner for the future'",
      "source": "France 24",
      "url": "https://www.france24.com/en/macron-always-been-a-strong-believer-in-the-importance-of-africa-as-a-partner-for-the-future",
      "published_date": "2026-05-11T19:04:30+00:00",
      "category": "Diplomacy"
    },
    {
      "title": "Exclusive: Emmanuel Macron interview on FRANCE 24, Tuesday May 12 at 9pm",
      "source": "France 24",
      "url": "https://www.france24.com/en/africa/20260511-exclusive-interview-french-president-macron-tuesday-may-12-9-pm",
      "published_date": "2026-05-11T18:40:52+00:00",
      "category": "Diplomacy"
    },
    {
      "title": "Kenya summit represents 'demarcation point': France 'wants to do business' with African continent",
      "source": "France 24",
      "url": "https://www.france24.com/en/video/20260511-kenya-summit-represents-demarcation-point-france-wants-to-do-business-with-african-continent",
      "published_date": "2026-05-11T18:37:00+00:00",
      "category": "Diplomacy"
    },
    {
      "title": "Poland says it expects US to extradite ex-minister who fled from Hungary",
      "source": "The Guardian",
      "url": "https://www.theguardian.com/world/2026/may/11/polish-ex-minister-zbigniew-ziobro-flees-hungary-usa",
      "published_date": "2026-05-11T17:28:23+00:00",
      "category": "Diplomacy"
    },
    {
      "title": "'Britain at the heart of Europe': How Starmer's plans are going down in the EU",
      "source": "BBC News",
      "url": "https://www.bbc.com/news/articles/cwy2k7re9jdo?at_medium=RSS&at_campaign=rss",
      "published_date": "2026-05-11T17:15:52+00:00",
      "category": "Diplomacy"
    },
    {
      "title": "New direct ferry service to launch between France and Ireland",
      "source": "The Local France",
      "url": "https://www.thelocal.fr/20260511/new-ferry-company-to-launch-service-between-france-and-ireland",
      "published_date": "2026-05-11T16:35:45+00:00",
      "category": "Diplomacy"
    },
    {
      "title": "Starmer to reset Labour agenda, bring UK back to the 'heart of Europe'",
      "source": "RFI English",
      "url": "https://www.rfi.fr/en/international/20260511-starmer-to-reset-labour-agenda-bring-uk-back-to-the-heart-of-europe",
      "published_date": "2026-05-11T16:25:23+00:00",
      "category": "Diplomacy"
    },
    {
      "title": "'Total lack of respect': Macron interrupts speaker to ask for silence",
      "source": "BBC News",
      "url": "https://www.bbc.com/news/videos/czx2wd20evyo?at_medium=RSS&at_campaign=rss",
      "published_date": "2026-05-11T16:10:18+00:00",
      "category": "Diplomacy"
    },
    {
      "title": "Macron champions African investment, backs restitution of colonial artefacts",
      "source": "RFI English",
      "url": "https://www.rfi.fr/en/africa/20260511-macron-champions-african-investment-backs-restitution-of-colonial-artefacts",
      "published_date": "2026-05-11T16:06:39+00:00",
      "category": "Diplomacy"
    },
    {
      "title": "Macron announces €23 billion investment in Africa at Kenya summit",
      "source": "France 24",
      "url": "https://www.france24.com/en/africa/20260511-macron-announces-23-billion-euro-investment-in-africa-at-kenya-summit",
      "published_date": "2026-05-11T15:53:13+00:00",
      "category": "Diplomacy"
    },
    {
      "title": "EU preparing to offer key concession to UK in new post-Brexit agricultural deal",
      "source": "The Guardian",
      "url": "https://www.theguardian.com/world/2026/may/11/brussels-eu-uk-concession-agricultural-deal-live-animal-exports",
      "published_date": "2026-05-11T15:30:44+00:00",
      "category": "Diplomacy"
    },
    {
      "title": "Starmer pledges to bring Britain closer to the EU as he faces calls to step down",
      "source": "France 24",
      "url": "https://www.france24.com/en/video/20260511-starmer-pledges-to-bring-britain-closer-to-the-eu-as-he-faces-calls-to-step-down",
      "published_date": "2026-05-11T15:24:48+00:00",
      "category": "Diplomacy"
    },
    {
      "title": "Africa Forward Summit in Kenya: France offers ‘third way’ in Africa’s AI race",
      "source": "France 24",
      "url": "https://www.france24.com/en/video/20260511-africa-forward-summit-in-kenya-france-offers-third-way-in-africa-s-ai-race",
      "published_date": "2026-05-11T15:01:56+00:00",
      "category": "Diplomacy"
    },
    {
      "title": "EU approves new sanctions on Israeli settlers over West Bank violence",
      "source": "France 24",
      "url": "https://www.france24.com/en/europe/20260511-eu-approves-new-sanctions-on-israeli-settlers-over-west-bank-violence-palestinians",
      "published_date": "2026-05-11T13:49:57+00:00",
      "category": "Diplomacy"
    },
    {
      "title": "EU’s Kallas criticises Putin’s ‘very cynical’ Ukraine ceasefire calls and rejects suggestion of Schröder as mediator – Europe live",
      "source": "The Guardian",
      "url": "https://www.theguardian.com/world/live/2026/may/11/ukraine-russia-eu-ministers-brussels-putin-zelenskyy-hantavirus-spain-europe-latest-news-updates",
      "published_date": "2026-05-11T13:23:17+00:00",
      "category": "Diplomacy"
    },
    {
      "title": "Bosnia's powerful peace envoy quits, with questions over role's future",
      "source": "BBC News",
      "url": "https://www.bbc.com/news/articles/cg5pvj5pg51o?at_medium=RSS&at_campaign=rss",
      "published_date": "2026-05-11T13:14:30+00:00",
      "category": "Diplomacy"
    },
    {
      "title": "'I will make order': Macorn calls for silence at Africa summit",
      "source": "France 24",
      "url": "https://www.france24.com/en/video/20260511-i-will-make-order-macorn-calls-for-silence-at-africa-summit",
      "published_date": "2026-05-11T13:11:10+00:00",
      "category": "Diplomacy"
    },
    {
      "title": "Starmer vows to prove 'doubters' wrong,  bring UK closer to the EU to rescue his job",
      "source": "France 24",
      "url": "https://www.france24.com/en/video/20260511-starmer-vows-to-prove-doubters-wrong-bring-uk-closer-to-the-eu-to-rescue-his-job",
      "published_date": "2026-05-11T13:04:39+00:00",
      "category": "Diplomacy"
    },
    {
      "title": "Norway puts UN project funding on hold raising fears for plastics treaty talks",
      "source": "The Guardian",
      "url": "https://www.theguardian.com/environment/2026/may/11/norway-un-environment-programme-funding-plastics-treaty-talks",
      "published_date": "2026-05-11T11:20:08+00:00",
      "category": "Diplomacy"
    },
    {
      "title": "Ukraine and Russia fight on despite US-mediated ceasefire",
      "source": "France 24",
      "url": "https://www.france24.com/en/video/20260511-ukraine-and-russia-fight-on-despite-us-mediated-ceasefire",
      "published_date": "2026-05-11T14:35:57+00:00",
      "category": "Military"
    },
    {
      "title": "Sudan conflict enters 'deadlier' phase due to drones: UN",
      "source": "RFI English",
      "url": "https://www.rfi.fr/en/africa/20260511-sudan-conflict-enters-deadlier-phase-due-to-drones-un-civilan-deaths",
      "published_date": "2026-05-11T13:31:16+00:00",
      "category": "Military"
    },
    {
      "title": "Iran-US ceasefire grows shaky after Trump rejects Tehran's latest proposal",
      "source": "France 24",
      "url": "https://www.france24.com/en/video/20260511-iran-us-ceasefire-grows-shaky-after-trump-rejects-tehran-s-latest-proposal",
      "published_date": "2026-05-11T13:08:02+00:00",
      "category": "Military"
    },
    {
      "title": "Molière Ex Machina: AI used to create ‘new work’ by beloved French playwright",
      "source": "The Guardian",
      "url": "https://www.theguardian.com/stage/2026/may/11/moliere-ex-machina-ai-create-new-work-france-equivalent-shakespeare",
      "published_date": "2026-05-11T12:29:36+00:00",
      "category": "Military"
    },
    {
      "title": "EU rejects Putin call for Gerhard Schröder role in Ukraine peace talks",
      "source": "The Guardian",
      "url": "https://www.theguardian.com/world/2026/may/11/eu-rejects-putin-call-gerhard-schroder-role-ukraine-peace-talks",
      "published_date": "2026-05-11T12:02:36+00:00",
      "category": "Military"
    },
    {
      "title": "Trump rejects Iran's response to US peace proposal as 'unacceptable'",
      "source": "France 24",
      "url": "https://www.france24.com/en/video/20260511-trump-rejects-iran-s-response-to-us-peace-proposal-as-unacceptable",
      "published_date": "2026-05-11T10:53:09+00:00",
      "category": "Military"
    },
    {
      "title": "Suspected hantavirus case triggers emergency deployment to isolated island",
      "source": "France 24",
      "url": "https://www.france24.com/en/video/20260511-suspected-hantavirus-case-triggers-emergency-deployment-to-isolated-island",
      "published_date": "2026-05-11T10:50:17+00:00",
      "category": "Military"
    },
    {
      "title": "Russia, China and Iran: What do Beijing and Moscow want to gain from conflict?",
      "source": "France 24",
      "url": "https://www.france24.com/en/video/20260511-russia-china-and-iran-what-do-beijing-and-moscow-want-to-gain-from-conflict",
      "published_date": "2026-05-11T10:47:03+00:00",
      "category": "Military"
    },
    {
      "title": "Portrait looted by Nazis found in home of Dutch SS leader's descendants",
      "source": "BBC News",
      "url": "https://www.bbc.com/news/articles/cgmpj0p9k08o?at_medium=RSS&at_campaign=rss",
      "published_date": "2026-05-11T10:00:31+00:00",
      "category": "Military"
    },
    {
      "title": "US-Israel war on Iran: Hormuz island tourism takes a hit",
      "source": "France 24",
      "url": "https://www.france24.com/en/video/20260511-us-israel-war-on-iran-hormuz-island-tourism-takes-a-hit",
      "published_date": "2026-05-11T10:00:18+00:00",
      "category": "Military"
    },
    {
      "title": "My Father’s Diaries review – haunting home-video excavates trauma of Srebrenica massacre",
      "source": "The Guardian",
      "url": "https://www.theguardian.com/film/2026/may/11/my-fathers-diaries-review-ado-hasanovic-bosnian-war-srebrenica",
      "published_date": "2026-05-11T06:00:47+00:00",
      "category": "Military"
    },
    {
      "title": "Iran’s two navies and the fate of its “Midget Submarines”",
      "source": "France 24",
      "url": "https://www.france24.com/en/tv-shows/spotlight/20260510-iran-s-two-navies-and-the-fate-of-its-midget-submarines",
      "published_date": "2026-05-10T17:46:05+00:00",
      "category": "Military"
    },
    {
      "title": "Inside the chimpanzee 'civil war' that has locked a Ugandan forest in conflict",
      "source": "RFI English",
      "url": "https://www.rfi.fr/en/africa/20260510-inside-the-chimpanzee-civil-war-that-s-locked-a-ugandan-forest-in-conflict",
      "published_date": "2026-05-10T16:24:30+00:00",
      "category": "Military"
    },
    {
      "title": "Europe weighs Putin’s ceasefire signals and security proposals",
      "source": "France 24",
      "url": "https://www.france24.com/en/europe-weighs-putin-s-ceasefire-signals-and-security-proposals",
      "published_date": "2026-05-10T15:27:08+00:00",
      "category": "Military"
    },
    {
      "title": "Russia, Ukraine trade blame over ceasefire violations",
      "source": "France 24",
      "url": "https://www.france24.com/en/russia-ukraine-trade-blame-over-ceasefire-violations",
      "published_date": "2026-05-10T15:00:21+00:00",
      "category": "Military"
    },
    {
      "title": "Berlin sceptical as Putin proposes Germany's ex-chancellor Schroeder as Ukraine mediator",
      "source": "France 24",
      "url": "https://www.france24.com/en/europe/20260510-berlin-sceptical-as-putin-proposes-ex-german-chancellor-schroeder-as-ukraine-mediator",
      "published_date": "2026-05-10T14:03:25+00:00",
      "category": "Military"
    },
    {
      "title": "Putin says he thinks Ukraine conflict 'coming to an end'",
      "source": "BBC News",
      "url": "https://www.bbc.com/news/articles/cn8p4j2jzwwo?at_medium=RSS&at_campaign=rss",
      "published_date": "2026-05-10T13:56:43+00:00",
      "category": "Military"
    },
    {
      "title": "Prague derby abandoned after fans storm pitch with Slavia seconds from title",
      "source": "The Guardian",
      "url": "https://www.theguardian.com/football/2026/may/10/slavia-sparta-prague-derby-abandoned-fans-storm-pitch-title",
      "published_date": "2026-05-10T12:36:26+00:00",
      "category": "Military"
    },
    {
      "title": "First plane carrying passengers evacuated from hantavirus-hit cruise ship has left Tenerife – Europe live",
      "source": "The Guardian",
      "url": "https://www.theguardian.com/world/live/2026/may/10/hantavirus-cruise-ship-rat-spain-tenerife-russia-ukraine-putin-zelenskyy-war-europe-latest-news-updates",
      "published_date": "2026-05-10T11:34:23+00:00",
      "category": "Military"
    },
    {
      "title": "Vladimir Putin suggests Ukraine war is ‘coming to an end’",
      "source": "The Guardian",
      "url": "https://www.theguardian.com/world/2026/may/10/vladimir-putin-suggests-ukraine-war-is-coming-to-an-end",
      "published_date": "2026-05-10T10:56:11+00:00",
      "category": "Military"
    },
    {
      "title": "Starmer announces plans to fully nationalise British Steel",
      "source": "France 24",
      "url": "https://www.france24.com/en/tv-shows/business/20260511-starmer-announces-plans-to-fully-nationalise-british-steel",
      "published_date": "2026-05-11T20:52:19+00:00",
      "category": "Energy"
    },
    {
      "title": "India: Modi wants Indians to stop buying gold",
      "source": "France 24",
      "url": "https://www.france24.com/en/video/20260511-india-modi-wants-indians-to-stop-buying-gold",
      "published_date": "2026-05-11T16:06:42+00:00",
      "category": "Energy"
    },
    {
      "title": "Trump calls Iran's response to US peace proposal 'totally unacceptable'",
      "source": "France 24",
      "url": "https://www.france24.com/en/middle-east/20260510-trump-calls-iran-response-to-us-peace-proposal-totally-unacceptable",
      "published_date": "2026-05-10T23:23:51+00:00",
      "category": "Energy"
    },
    {
      "title": "‘We are talking about energy security for Europe’: Norway doubles down on oil and gas production",
      "source": "The Guardian",
      "url": "https://www.theguardian.com/world/2026/may/09/norway-oil-and-gas-production-shortages-middle-east-ukraine",
      "published_date": "2026-05-09T06:00:49+00:00",
      "category": "Energy"
    },
    {
      "title": "Energy security vs climate crisis: Norway reopens three old gas fields",
      "source": "France 24",
      "url": "https://www.france24.com/en/energy-security-vs-climate-crisis-norway-reopens-three-old-gas-fields",
      "published_date": "2026-05-08T12:47:59+00:00",
      "category": "Energy"
    },
    {
      "title": "Airline emissions in Europe top pre-Covid levels despite pledge to decarbonise",
      "source": "The Guardian",
      "url": "https://www.theguardian.com/environment/2026/may/08/airline-emissions-in-europe-top-pre-covid-levels-despite-pledge-to-decarbonise",
      "published_date": "2026-05-08T10:30:25+00:00",
      "category": "Energy"
    },
    {
      "title": "Our cities are choked by cars – here’s how experts would fix them",
      "source": "The Guardian",
      "url": "https://www.theguardian.com/environment/2026/may/08/cities-cars-experts-green-spaces-cyclists",
      "published_date": "2026-05-08T10:00:25+00:00",
      "category": "Energy"
    },
    {
      "title": "Argentina probes link to deadly hantavirus outbreak on Atlantic cruise",
      "source": "France 24",
      "url": "https://www.france24.com/en/video/20260507-argentina-probes-link-to-deadly-hantavirus-outbreak-on-atlantic-cruise",
      "published_date": "2026-05-07T09:38:14+00:00",
      "category": "Energy"
    },
    {
      "title": "Hantavirus on the rise in Argentina, where MV Hondius cruise ship set sail",
      "source": "France 24",
      "url": "https://www.france24.com/en/americas/20260507-hantavirus-on-rise-argentina-where-mv-hondius-cruise-ship-set-sail",
      "published_date": "2026-05-07T08:32:37+00:00",
      "category": "Energy"
    },
    {
      "title": "France considers windfall tax on massive oil profits: TotalEnergies fights back",
      "source": "France 24",
      "url": "https://www.france24.com/en/france-considers-windfall-tax-on-massive-oil-profits-totalenergies-fights-back",
      "published_date": "2026-05-06T15:30:00+00:00",
      "category": "Energy"
    },
    {
      "title": "Norwegian government attacked over decision to reopen North Sea gasfields",
      "source": "The Guardian",
      "url": "https://www.theguardian.com/business/2026/may/06/norwegian-government-rebuked-over-decision-to-reopen-north-sea-gas-fields",
      "published_date": "2026-05-06T15:25:36+00:00",
      "category": "Energy"
    },
    {
      "title": "France’s EDF to test ‘dynamic’ electricity pricing",
      "source": "The Local France",
      "url": "https://www.thelocal.fr/20260506/frances-edf-to-test-dynamic-electricity-pricing",
      "published_date": "2026-05-06T12:35:37+00:00",
      "category": "Energy"
    },
    {
      "title": "Samsung Electronics reaches $1 trillion market cap thanks to surging demand for AI chips",
      "source": "France 24",
      "url": "https://www.france24.com/en/tv-shows/business/20260506-samsung-electronics-reaches-1-trillion-market-cap-thanks-to-surging-demand-for-ai-chips",
      "published_date": "2026-05-06T08:37:10+00:00",
      "category": "Energy"
    },
    {
      "title": "Hantavirus cruise ship passengers enter isolation facility after evacuation to UK",
      "source": "The Guardian",
      "url": "https://www.theguardian.com/world/2026/may/11/mv-hondius-passengers-from-hantavirus-cruise-ship-enter-isolation-facility-in-wirral",
      "published_date": "2026-05-11T08:06:03+00:00",
      "category": "Economy"
    },
    {
      "title": "‘Degree of complacency’: are supply chains prepared for impact of ongoing Iran war?",
      "source": "The Guardian",
      "url": "https://www.theguardian.com/business/2026/may/10/degree-complacency-supply-chains-prepared-impact-iran-war",
      "published_date": "2026-05-10T14:00:27+00:00",
      "category": "Economy"
    },
    {
      "title": "Tax deadlines, rail trips and summer drinks: 6 essential articles for life in France",
      "source": "The Local France",
      "url": "https://www.thelocal.fr/20260510/tax-deadlines-rail-trips-and-summer-drinks-6-essential-articles-for-life-in-france",
      "published_date": "2026-05-10T08:07:23+00:00",
      "category": "Economy"
    },
    {
      "title": "Away from the red carpet, the  ‘flashy, jazzy and tacky’ descend on Cannes – photo essay",
      "source": "The Guardian",
      "url": "https://www.theguardian.com/artanddesign/2026/may/10/cannes-film-festival-sidelines-photo-essay",
      "published_date": "2026-05-10T06:00:18+00:00",
      "category": "Economy"
    },
    {
      "title": "How Africa helped forge French billionaire Vincent Bolloré's empire of influence",
      "source": "RFI English",
      "url": "https://www.rfi.fr/en/france/20260508-how-africa-helped-forge-french-billionaire-vincent-bollore-s-empire-of-influence",
      "published_date": "2026-05-08T16:00:58+00:00",
      "category": "Economy"
    },
    {
      "title": "Iran and the US trade fire over Hormuz, Trump says ceasefire still in effect",
      "source": "France 24",
      "url": "https://www.france24.com/en/iran-and-the-us-trade-fire-over-hormuz-trump-says-ceasefire-still-in-effect",
      "published_date": "2026-05-08T09:45:52+00:00",
      "category": "Economy"
    },
    {
      "title": "Israel and Hezbollah continue to trade blows despite the ceasefire",
      "source": "France 24",
      "url": "https://www.france24.com/en/israel-and-hezbollah-continue-to-trade-blows-despite-the-ceasefire",
      "published_date": "2026-05-08T09:41:34+00:00",
      "category": "Economy"
    },
    {
      "title": "Iran on the verge of economic asphyxiation -- rare footage from Tehran",
      "source": "France 24",
      "url": "https://www.france24.com/en/did-donald-trump-liberate-the-iranian-people-iran-on-the-verge-of-economic-asphyxiation",
      "published_date": "2026-05-08T09:11:00+00:00",
      "category": "Economy"
    },
    {
      "title": "US trade court once again rules Trump tariffs illegal, but issues narrow block",
      "source": "France 24",
      "url": "https://www.france24.com/en/americas/20260508-us-trade-court-once-again-rules-trump-tariffs-illegal-but-issues-narrow-block",
      "published_date": "2026-05-08T07:28:01+00:00",
      "category": "Economy"
    },
    {
      "title": "‘Being human helps’: despite rise of AI is there still hope for Europe’s translators?",
      "source": "The Guardian",
      "url": "https://www.theguardian.com/technology/2026/may/08/being-human-helps-despite-rise-of-ai-is-there-still-hope-for-europes-translators",
      "published_date": "2026-05-08T04:00:37+00:00",
      "category": "Economy"
    },
    {
      "title": "Travel costs soar for Champions League final",
      "source": "France 24",
      "url": "https://www.france24.com/en/travel-costs-soar-for-champions-league-final",
      "published_date": "2026-05-07T21:06:59+00:00",
      "category": "Economy"
    },
    {
      "title": "Trump's 'irresponsible war' to blame for economic slowdown, German minister says",
      "source": "BBC News",
      "url": "https://www.bbc.com/news/articles/cwy2d0v3p2po?at_medium=RSS&at_campaign=rss",
      "published_date": "2026-05-07T18:13:11+00:00",
      "category": "Economy"
    },
    {
      "title": "Inside Iran’s new two-tier internet access, as blackout drags on",
      "source": "RFI English",
      "url": "https://www.rfi.fr/en/international/20260507-inside-iran-s-new-two-tier-internet-as-blackout-drags-on",
      "published_date": "2026-05-07T16:01:28+00:00",
      "category": "Economy"
    },
    {
      "title": "JD Sports says Iran war could hit consumer spending and raise prices",
      "source": "The Guardian",
      "url": "https://www.theguardian.com/business/2026/may/07/jd-sports-warns-iran-war-could-hit-consumer-spending-and-raise-prices",
      "published_date": "2026-05-07T09:02:58+00:00",
      "category": "Economy"
    },
    {
      "title": "French rail unions announce June train strike",
      "source": "The Local France",
      "url": "https://www.thelocal.fr/20260507/french-rail-unions-announce-june-train-strike",
      "published_date": "2026-05-07T06:45:37+00:00",
      "category": "Economy"
    },
    {
      "title": "Putin said to be 'hiding in bunkers' as his popularity erodes",
      "source": "France 24",
      "url": "https://www.france24.com/en/tv-shows/press-review/20260506-putin-said-to-be-hiding-in-bunkers-as-his-popularity-erodes",
      "published_date": "2026-05-06T09:50:06+00:00",
      "category": "Economy"
    },
    {
      "title": "G7 ministers discuss trade security and China dependence in Paris",
      "source": "RFI English",
      "url": "https://www.rfi.fr/en/international/20260506-g7-ministers-discuss-trade-security-and-china-dependence-in-paris",
      "published_date": "2026-05-06T06:54:31+00:00",
      "category": "Economy"
    },
    {
      "title": "Amazon to invest €15bn in France expansion",
      "source": "The Local France",
      "url": "https://www.thelocal.fr/20260506/amazon-to-invest-e15bn-in-france-expansion",
      "published_date": "2026-05-06T06:45:01+00:00",
      "category": "Economy"
    },
    {
      "title": "‘Stuck in the mud’: one year on, Friedrich Merz struggles to find his footing",
      "source": "The Guardian",
      "url": "https://www.theguardian.com/world/2026/may/06/stuck-in-the-mud-one-year-on-friedrich-merz-struggles-to-find-his-footing",
      "published_date": "2026-05-06T04:00:03+00:00",
      "category": "Economy"
    },
    {
      "title": "G7 trade ministers meet in Paris as global tensions and tariff threats mount",
      "source": "France 24",
      "url": "https://www.france24.com/en/europe/20260505-g7-trade-ministers-meet-in-paris-as-global-tensions-and-tariff-threats-mount",
      "published_date": "2026-05-05T23:50:51+00:00",
      "category": "Economy"
    },
    {
      "title": "Pressure mounts on British PM Starmer to quit after crushing Labour election losses",
      "source": "France 24",
      "url": "https://www.france24.com/en/europe/20260511-pressure-mounts-on-british-pm-starmer-to-quit-after-crushing-labour-election-losses",
      "published_date": "2026-05-11T23:13:16+00:00",
      "category": "Local Events"
    },
    {
      "title": "France arrests Tunisian suspected of planning 'jihad-inspired' attack in Paris",
      "source": "France 24",
      "url": "https://www.france24.com/en/france/20260511-france-arrests-tunisian-suspected-of-planning-jihad-inspired-attack-in-paris",
      "published_date": "2026-05-11T20:16:09+00:00",
      "category": "Local Events"
    },
    {
      "title": "Royal Opera House calls for release of Georgian bass singer jailed over democracy protests",
      "source": "The Guardian",
      "url": "https://www.theguardian.com/culture/2026/may/11/royal-opera-house-release-paata-burchuladze-georgian-singer-democracy-protests-tbilisi",
      "published_date": "2026-05-11T15:00:58+00:00",
      "category": "Local Events"
    },
    {
      "title": "Hantavirus: French PM Lecornu holds talks with medical advisers, ministers",
      "source": "France 24",
      "url": "https://www.france24.com/en/video/20260511-hantavirus-french-pm-lecornu-holds-talks-with-medical-advisers-ministers",
      "published_date": "2026-05-11T14:33:58+00:00",
      "category": "Local Events"
    },
    {
      "title": "Spain, Ireland, Slovenia will not broadcast Eurovision over Israel's participation",
      "source": "France 24",
      "url": "https://www.france24.com/en/culture/20260511-spain-ireland-slovenia-will-not-broadcast-eurovision-to-protest-israel-s-inclusion",
      "published_date": "2026-05-11T13:55:43+00:00",
      "category": "Local Events"
    },
    {
      "title": "Evacuated US and French MV Hondius passengers test positive for hantavirus",
      "source": "The Guardian",
      "url": "https://www.theguardian.com/world/2026/may/11/evacuated-us-and-french-mv-hondius-cruise-ship-passengers-test-positive-for-hantavirus",
      "published_date": "2026-05-11T13:37:30+00:00",
      "category": "Local Events"
    },
    {
      "title": "US and French nationals test positive for hantavirus after leaving ship",
      "source": "BBC News",
      "url": "https://www.bbc.com/news/articles/cjep78l5835o?at_medium=RSS&at_campaign=rss",
      "published_date": "2026-05-11T13:13:22+00:00",
      "category": "Local Events"
    },
    {
      "title": "UK's Starmer promises to be bolder to try to rescue his job",
      "source": "France 24",
      "url": "https://www.france24.com/en/video/20260511-uk-s-starmer-promises-to-be-bolder-to-try-to-rescue-his-job",
      "published_date": "2026-05-11T13:08:56+00:00",
      "category": "Local Events"
    },
    {
      "title": "‘It’s organised intimidation’: New wave of anti-migrant violence sweeps South Africa",
      "source": "France 24",
      "url": "https://www.france24.com/en/africa/20260511-organised-intimidation-new-wave-anti-migrant-violence-south-africa",
      "published_date": "2026-05-11T12:26:02+00:00",
      "category": "Local Events"
    },
    {
      "title": "PM Starmer clings on to power as Labour rivals make moves",
      "source": "France 24",
      "url": "https://www.france24.com/en/tv-shows/press-review/20260511-pm-starmer-clings-on-to-power-as-labour-rivals-make-moves",
      "published_date": "2026-05-11T10:49:52+00:00",
      "category": "Local Events"
    },
    {
      "title": "Hantavirus outbreak: US, French nationals test positive after evacuating ship",
      "source": "France 24",
      "url": "https://www.france24.com/en/video/20260511-hantavirus-outbreak-us-french-nationals-test-positive-after-evacuating-ship",
      "published_date": "2026-05-11T10:49:16+00:00",
      "category": "Local Events"
    },
    {
      "title": "French passenger from hantavirus ship tests positive",
      "source": "France 24",
      "url": "https://www.france24.com/en/video/20260511-french-passenger-from-hantavirus-ship-tests-positive",
      "published_date": "2026-05-11T10:45:51+00:00",
      "category": "Local Events"
    },
    {
      "title": "Britain’s Starmer vows to prove ‘doubters’ wrong as he fights ouster calls",
      "source": "France 24",
      "url": "https://www.france24.com/en/europe/20260511-britain-starmer-vows-to-prove-doubters-wrong-as-he-fights-ouster-calls",
      "published_date": "2026-05-11T10:13:57+00:00",
      "category": "Local Events"
    },
    {
      "title": "REPLAY: Under-pressure UK PM addresses nation after election losses",
      "source": "France 24",
      "url": "https://www.france24.com/en/video/20260511-replay-under-pressure-uk-pm-addresses-nation-after-election-losses",
      "published_date": "2026-05-11T10:09:47+00:00",
      "category": "Local Events"
    },
    {
      "title": "Eurovision fever hits host city Vienna",
      "source": "France 24",
      "url": "https://www.france24.com/en/video/20260511-eurovision-fever-hits-host-city-vienna",
      "published_date": "2026-05-11T10:08:38+00:00",
      "category": "Local Events"
    },
    {
      "title": "Hantavirus outbreak renews painful memories for Patagonian village",
      "source": "France 24",
      "url": "https://www.france24.com/en/video/20260511-hantavirus-outbreak-renews-painful-memories-for-patagonian-village",
      "published_date": "2026-05-11T10:05:28+00:00",
      "category": "Local Events"
    },
    {
      "title": "Everything you need to know about swimming in the Seine in summer 2026",
      "source": "The Local France",
      "url": "https://www.thelocal.fr/20260511/everything-you-need-to-know-about-swimming-in-the-seine-in-summer-2026",
      "published_date": "2026-05-11T09:25:40+00:00",
      "category": "Local Events"
    },
    {
      "title": "Seine swimming to return to Paris this summer",
      "source": "The Local France",
      "url": "https://www.thelocal.fr/20260511/seine-swimming-to-return-to-paris-this-summer",
      "published_date": "2026-05-11T07:46:37+00:00",
      "category": "Local Events"
    },
    {
      "title": "Starmer under pressure: “Swapping leaders won’t fix problems,” says former Labour adviser",
      "source": "France 24",
      "url": "https://www.france24.com/en/tv-shows/spotlight/20260510-starmer-under-pressure-swapping-leaders-won-t-fix-problems-says-former-labour-adviser",
      "published_date": "2026-05-10T21:55:36+00:00",
      "category": "Local Events"
    },
    {
      "title": "Dozens of people from cruise ship struck by hantavirus leave Tenerife",
      "source": "The Guardian",
      "url": "https://www.theguardian.com/world/2026/may/10/hantavirus-cruise-ship-tenerife-evacuate-passengers-mv-hondius",
      "published_date": "2026-05-10T20:30:22+00:00",
      "category": "Local Events"
    }
  ]
}